central_tools/__init__.py
central_tools/config.py
central_tools/estimators.py
central_tools/exceptions.py
central_tools/model_limits.py
central_tools/models.py
central_tools/orchestrator.py
central_tools/placeholders.py
central_tools/config/redis_settings.py
central_tools/cycling/__init__.py
central_tools/cycling/api_cycler.py
central_tools/cycling/redis_tracker.py
central_tools/cycling/usage_tracker.py
central_tools/integrations/__init__.py
central_tools/integrations/redis_tracker.py
central_tools/monitoring/__init__.py
central_tools/monitoring/http.py
central_tools/providers/__init__.py
central_tools/providers/base.py
central_tools/providers/google.py
central_tools/retry/__init__.py
central_tools/retry/strategies.py
central_tools/routing/__init__.py
central_tools/routing/router.py
central_tools/routing/smart_router.py
central_tools_llm-2025.11.0.dist-info/METADATA
central_tools_llm-2025.11.0.dist-info/WHEEL
central_tools_llm-2025.11.0.dist-info/top_level.txt
central_tools_llm-2025.11.0.dist-info/RECORD
