Metadata-Version: 2.4
Name: central-tools-llm
Version: 2025.11.0
Summary: Centralized routing, retry, and API cycling utilities for LLM integrations
Author: Central Tools Team
Keywords: llm,routing,retry,rate-limiting,gemini,gemma
Classifier: Programming Language :: Python :: 3
Classifier: License :: OSI Approved :: MIT License
Classifier: Operating System :: OS Independent
Requires-Python: >=3.10
Requires-Dist: httpx<0.29,>=0.27
Provides-Extra: google
Requires-Dist: google-generativeai>=0.8.5; extra == "google"
